setup.py
phil_gnb_distributions/Binomialdistribution.py
phil_gnb_distributions/Gaussiandistribution.py
phil_gnb_distributions/Generaldistribution.py
phil_gnb_distributions/__init__.py
phil_gnb_distributions.egg-info/PKG-INFO
phil_gnb_distributions.egg-info/SOURCES.txt
phil_gnb_distributions.egg-info/dependency_links.txt
phil_gnb_distributions.egg-info/not-zip-safe
phil_gnb_distributions.egg-info/top_level.txt