Metadata-Version: 1.0
Name: phil-gnb-distributions
Version: 0.1
Summary: Gaussian and Binomial distributions
Home-page: UNKNOWN
Author: Philemon Johnson
Author-email: philjohnon96@gmail.com
License: UNKNOWN
Platform: UNKNOWN
